proyecto_primera_api/__init__.py
proyecto_primera_api/courses.py
proyecto_primera_api/utils.py
proyecto_primera_api-0.1.0.dist-info/METADATA
proyecto_primera_api-0.1.0.dist-info/WHEEL
proyecto_primera_api-0.1.0.dist-info/top_level.txt
proyecto_primera_api-0.1.0.dist-info/RECORD
