Metadata-Version: 2.2
Name: proyecto_primera_api
Version: 0.1.0
Summary: Biblioteca consultas
Home-page: https://hack4u.io
Author: el_loco_lala
Dynamic: author
Dynamic: description-content-type
Dynamic: home-page
Dynamic: summary
